simuladorCuentaBancaria/__init__.py
simuladorCuentaBancaria/funciones.py
simuladorcuentabancaria-0.1.1.dist-info/licenses/LICENSE
simuladorcuentabancaria-0.1.1.dist-info/METADATA
simuladorcuentabancaria-0.1.1.dist-info/WHEEL
simuladorcuentabancaria-0.1.1.dist-info/top_level.txt
simuladorcuentabancaria-0.1.1.dist-info/RECORD
