Metadata-Version: 2.4
Name: simuladorCuentaBancaria
Version: 0.1.1
Summary: Simulador Cuenta Bancaria
Author: Nicolás Guañuna y Alex Valdez
Requires-Python: >=3.8
License-File: LICENSE
Dynamic: license-file
